kani/ext/vision/__init__.py
kani/ext/vision/cli.py
kani/ext/vision/exceptions.py
kani/ext/vision/parts.py
kani/ext/vision/utils.py
kani/ext/vision/engines/__init__.py
kani/ext/vision/engines/llava/__init__.py
kani/ext/vision/engines/llava/engine.py
kani/ext/vision/engines/openai/__init__.py
kani/ext/vision/engines/openai/engine.py
kani/ext/vision/engines/openai/img_tokens.py
kani/ext/vision/engines/openai/models.py
kani_vision-0.6.3.dist-info/METADATA
kani_vision-0.6.3.dist-info/WHEEL
kani_vision-0.6.3.dist-info/licenses/LICENSE
kani_vision-0.6.3.dist-info/RECORD
