Metadata-Version: 2.1
Name: kani-vision
Version: 0.6.3
Summary: Kani extension for supporting vision-language models (VLMs). Comes with model-agnostic support for GPT-Vision and LLaVA.
Project-URL: Homepage, https://github.com/zhudotexe/kani-vision
Project-URL: Bug Tracker, https://github.com/zhudotexe/kani-vision/issues
Author-email: Andrew Zhu <andrew@zhu.codes>
License: MIT License
License-File: LICENSE
Classifier: Development Status :: 4 - Beta
Classifier: Intended Audience :: Science/Research
Classifier: License :: OSI Approved :: MIT License
Classifier: Operating System :: OS Independent
Classifier: Programming Language :: Python :: 3
Classifier: Topic :: Scientific/Engineering :: Artificial Intelligence
Requires-Python: >=3.10
Requires-Dist: kani<2.0.0,>=0.6.1
Requires-Dist: pillow<11.0.0,>=10.0.0
Provides-Extra: ascii
Requires-Dist: ascii-magic~=2.3.0; extra == 'ascii'
Provides-Extra: llava
Requires-Dist: accelerate~=0.23.0; extra == 'llava'
Requires-Dist: einops~=0.7.0; extra == 'llava'
Requires-Dist: kani[huggingface,llama]<2.0.0,>=0.6.1; extra == 'llava'
Requires-Dist: protobuf~=4.24.4; extra == 'llava'
Requires-Dist: transformers!=4.35.0,<5.0.0,>=4.0.0; extra == 'llava'
Provides-Extra: openai
Requires-Dist: kani[openai]<2.0.0,>=0.6.1; extra == 'openai'
